{"107570":{"button":"ActionButton8","key":"ALT+2","name":"风暴之锤","slotId":8},"107574":{"button":"MultiBarBottomLeftButton7","key":"7","name":"天神下凡","slotId":67},"1161":{"button":"LdgrTc6D1fhwq9FJRjMEYhanFr7xNCSaaR","key":"TAB","name":"挑战怒吼","slotId":60},"1215279":{"button":"MultiBarRightButton11","key":"=","name":"G-99疾飙飞车","slotId":35},"163201":{"button":"LdgrTc6D1fhwq9FJRjMEYhanFr7xNCSaaR","key":"D","name":"斩杀","slotId":50},"1680":{"button":"LdgrTc6D1fhwq9FJRjMEYhanFr7xNCSaaR","key":"X","name":"旋风斩","slotId":54},"202168":{"button":"MultiBarBottomLeftButton3","key":"F3","name":"胜利在望","slotId":63},"20243":{"button":"LdgrTc6D1fhwq9FJRjMEYhanFr7xNCSaaR","key":"G","name":"毁灭打击","slotId":53},"20572":{"button":"ActionButton10","key":"ALT+4","name":"血性狂怒","slotId":10},"23920":{"button":"LdgrTc6D1fhwq9FJRjMEYhanFr7xNCSaaR","key":"F","name":"法术反射","slotId":51},"23922":{"button":"ActionButton2","key":"2","name":"盾牌猛击","slotId":2},"355":{"button":"MultiBarBottomLeftButton1","key":"F1","name":"嘲讽","slotId":61},"376079":{"button":"ActionButton12","key":"ALT+6","name":"勇士之矛","slotId":12},"385952":{"button":"ActionButton7","key":"ALT+1","name":"盾牌冲锋","slotId":7},"46968":{"button":"MultiBarBottomLeftButton9","key":"C","name":"震荡波","slotId":69},"5246":{"button":"ActionButton6","key":"6","name":"破胆怒吼","slotId":6},"57755":{"button":"MultiBarBottomLeftButton8","key":"8","name":"英勇投掷","slotId":68},"6343":{"button":"MultiBarBottomLeftButton6","key":"F6","name":"雷霆一击","slotId":66},"6544":{"button":"LdgrTc6D1fhwq9FJRjMEYhanFr7xNCSaaR","key":"R","name":"英勇飞跃","slotId":52},"6572":{"button":"ActionButton1","key":"1","name":"复仇","slotId":1},"871":{"button":"LdgrTc6D1fhwq9FJRjMEYhanFr7xNCSaaR","key":"T","name":"盾墙","slotId":55}}